mrktmp/__init__.py
mrktmp/client.py
tgmrkt_api-0.1.0.dist-info/licenses/LICENSE
tgmrkt_api-0.1.0.dist-info/METADATA
tgmrkt_api-0.1.0.dist-info/WHEEL
tgmrkt_api-0.1.0.dist-info/top_level.txt
tgmrkt_api-0.1.0.dist-info/RECORD
